spycause/__init__.py
spycause/linear.py
spycause/nonlinear.py
spycause/preprocessing.py
spycause/simulator.py
spycause/stan/car.stan
spycause/stan/icar.stan
spycause/stan/iv.stan
spycause/stan/joint.stan
spycause/stan/joint_icar.stan
spycause/stan/logit.stan
spycause/stan/ols.stan
spycause/stan/spatial_logit.stan
spycause/tests/test_ols.py
spycause-0.0.1.dist-info/METADATA
spycause-0.0.1.dist-info/WHEEL
spycause-0.0.1.dist-info/licenses/LICENSE
spycause-0.0.1.dist-info/RECORD
