Metadata-Version: 2.1
Name: spycause
Version: 0.0.1
Summary: A module for spatial causal inference in Python.
Project-URL: Homepage, https://github.com/tdhoffman/spycause
Project-URL: Bug Tracker, https://github.com/tdhoffman/spycause/issues
Author-email: "Tyler D. Hoffman" <cause@tdhoffman.com>
License-File: LICENSE
Classifier: Operating System :: OS Independent
Classifier: Programming Language :: Python :: 3
Requires-Python: >=3.7
